fb22epubbot/__init__.py
fb22epubbot/bot.py
fb22epubbot/utils.py
fb22epubbot-0.14.dist-info/METADATA
fb22epubbot-0.14.dist-info/WHEEL
fb22epubbot-0.14.dist-info/entry_points.txt
fb22epubbot-0.14.dist-info/RECORD
